pyspark_event_correlation/__init__.py
pyspark_event_correlation/classifiers.py
pyspark_event_correlation/cumsum.py
pyspark_event_correlation/shewahart.py
pyspark_event_correlation-1.0.2.dist-info/METADATA
pyspark_event_correlation-1.0.2.dist-info/WHEEL
pyspark_event_correlation-1.0.2.dist-info/top_level.txt
pyspark_event_correlation-1.0.2.dist-info/RECORD
