Metadata-Version: 2.1
Name: pyspark-event-correlation
Version: 1.0.2
Summary: Event Correlation and Changing Detection Algorithm
Home-page: https://github.com/Intellia-SME/pyspark-event-correlation
Author: Jim Katris
Author-email: info@intellia.gr
License: Apache-2.0 License
Project-URL: Changelog, https://github.com/Intellia-SME/pyspark-event-correlation/blob/main/HISTORY.md
Project-URL: Twitter, https://twitter.com/intellia_gr
Project-URL: Bug Tracker, https://github.com/Intellia-SME/pyspark-event-correlation/issues
Keywords: pyspark
Platform: UNKNOWN
Classifier: Development Status :: 5 - Production/Stable
Classifier: Intended Audience :: Developers
Classifier: Intended Audience :: Science/Research
Classifier: Programming Language :: Python :: 3 :: Only
Classifier: License :: OSI Approved :: Apache Software License
Classifier: Operating System :: OS Independent
Classifier: Natural Language :: English
Requires-Python: >=3.6
Requires-Dist: pyspark (>=3.2.1)
Requires-Dist: pandas (>=1.4.0)
